dsws_client-1.1.3.dist-info/METADATA
dsws_client-1.1.3.dist-info/WHEEL
dsws_client-1.1.3.dist-info/entry_points.txt
dsws_client/__init__.py
dsws_client/client.py
dsws_client/config.py
dsws_client/converters.py
dsws_client/ds_request.py
dsws_client/ds_response.py
dsws_client/exceptions.py
dsws_client/parse.py
dsws_client/py.typed
dsws_client/value_objects/__init__.py
dsws_client/value_objects/enums.py
dsws_client/value_objects/types.py
dsws_client/version.py
dsws_client-1.1.3.dist-info/RECORD
