Metadata-Version: 2.1
Name: dsws-client
Version: 1.1.3
Summary: Python client for the Datastream Web Service API (DSWS)
Author-Email: ljnsn <info@ljnsn.com>
License: MIT
Requires-Python: <4.0,>=3.8
Requires-Dist: attrs>=23.1.0
Requires-Dist: httpx>=0.27.0
Requires-Dist: msgspec>=0.18.6
Requires-Dist: python-dotenv>=1.0.0
Requires-Dist: setuptools; python_version >= "3.12"
Requires-Dist: typing-extensions>=4.11.0; python_version < "3.10"
